instalooter/__init__.py
instalooter/__main__.py
instalooter/_impl.py
instalooter/_uadetect.py
instalooter/_utils.py
instalooter/batch.py
instalooter/looters.py
instalooter/medias.py
instalooter/pages.py
instalooter/pbar.py
instalooter/worker.py
instalooter/cli/__init__.py
instalooter/cli/constants.py
instalooter/cli/login.py
instalooter/cli/logutils.py
instalooter/cli/threadutils.py
instalooter/cli/time.py
instalooter/static/splash.html
instalooter-2.4.3.dist-info/COPYING
instalooter-2.4.3.dist-info/METADATA
instalooter-2.4.3.dist-info/WHEEL
instalooter-2.4.3.dist-info/entry_points.txt
instalooter-2.4.3.dist-info/top_level.txt
instalooter-2.4.3.dist-info/zip-safe
instalooter-2.4.3.dist-info/RECORD
