Metadata-Version: 2.1
Name: instalooter
Version: 2.4.3
Summary: Another API-less Instagram pictures and videos downloader
Home-page: https://github.com/althonos/instalooter
Author: Martin Larralde
Author-email: martin.larralde@ens-paris-saclay.fr
License: GPLv3+
Keywords: instagram,download,web,web scraping,looter
Platform: any
Classifier: Development Status :: 4 - Beta
Classifier: Intended Audience :: Developers
Classifier: Intended Audience :: End Users/Desktop
Classifier: License :: OSI Approved :: GNU General Public License v3 or later (GPLv3+)
Classifier: Programming Language :: Python
Classifier: Programming Language :: Python :: 2.7
Classifier: Programming Language :: Python :: 3.3
Classifier: Programming Language :: Python :: 3.4
Classifier: Programming Language :: Python :: 3.5
Classifier: Programming Language :: Python :: 3.6
Classifier: Topic :: Internet
Classifier: Topic :: Software Development :: Libraries :: Python Modules
Classifier: Operating System :: OS Independent
Requires-Python: !=3.0.*,!=3.1.*,!=3.2.*,!=3.5.1,>=2.7
Requires-Dist: coloredlogs (~=10.0)
Requires-Dist: python-dateutil (~=2.1)
Requires-Dist: docopt (~=0.4)
Requires-Dist: fs (~=2.1)
Requires-Dist: requests (~=2.18)
Requires-Dist: six (~=1.4)
Requires-Dist: tqdm (~=4.19)
Requires-Dist: tenacity (~=6.0)
Requires-Dist: verboselogs (~=1.7)
Requires-Dist: typing (~=3.6) ; python_version < "3.6"
Provides-Extra: all
Requires-Dist: piexif ; extra == 'all'
Requires-Dist: Pillow ; extra == 'all'
Provides-Extra: coverage
Requires-Dist: coverage ; extra == 'coverage'
Requires-Dist: codecov ; extra == 'coverage'
Requires-Dist: codacy-coverage ; extra == 'coverage'
Provides-Extra: dev
Requires-Dist: docutils ; extra == 'dev'
Requires-Dist: Pygments ; extra == 'dev'
Requires-Dist: contexter (~=0.1) ; extra == 'dev'
Requires-Dist: parameterized (~=0.6) ; extra == 'dev'
Requires-Dist: green (~=2.12) ; extra == 'dev'
Requires-Dist: piexif ; extra == 'dev'
Requires-Dist: Pillow ; extra == 'dev'
Requires-Dist: coverage ; extra == 'dev'
Requires-Dist: codecov ; extra == 'dev'
Requires-Dist: codacy-coverage ; extra == 'dev'
Requires-Dist: mock (~=2.0) ; (python_version < "3.4") and extra == 'dev'
Provides-Extra: doc
Requires-Dist: sphinx (~=1.7) ; extra == 'doc'
Requires-Dist: sphinx-bootstrap-theme (~=0.6) ; extra == 'doc'
Requires-Dist: semantic-version (~=2.6) ; extra == 'doc'
Provides-Extra: metadata
Requires-Dist: piexif ; extra == 'metadata'
Requires-Dist: Pillow ; extra == 'metadata'
Provides-Extra: test
Requires-Dist: contexter (~=0.1) ; extra == 'test'
Requires-Dist: parameterized (~=0.6) ; extra == 'test'
Requires-Dist: green (~=2.12) ; extra == 'test'
Requires-Dist: piexif ; extra == 'test'
Requires-Dist: Pillow ; extra == 'test'
Requires-Dist: mock (~=2.0) ; (python_version < "3.4") and extra == 'test'
